MANIFEST.in
README.rst
requirements-dev.txt
setup.py
git_heimdall.egg-info/PKG-INFO
git_heimdall.egg-info/SOURCES.txt
git_heimdall.egg-info/dependency_links.txt
git_heimdall.egg-info/entry_points.txt
git_heimdall.egg-info/requires.txt
git_heimdall.egg-info/top_level.txt
heimdall/__init__.py
heimdall/__main__.py
heimdall/baseconfig.yaml
heimdall/baseconfig1.yaml
heimdall/config.py
heimdall/manager.py
heimdall/util.py
heimdall/codescan/__init__.py
heimdall/codescan/manager.py
heimdall/codescan/plugins/__init__.py
heimdall/codescan/plugins/base64_entropy.py
heimdall/codescan/plugins/check_regex.py
heimdall/codescan/plugins/entropy.py
heimdall/codescan/plugins/manager.py
heimdall/codescan/plugins/scan.py
heimdall/codescan/plugins/secrets_checker.py
heimdall/res/example.json.mustache
heimdall/res/example.xml.mustache
heimdall/res/example.yaml.mustache
heimdall/res/regex.json
heimdall/res/secrets.json
heimdall/res/secrets.xml
heimdall/res/secrets.yaml
heimdall/res/heimdall/hooks/heimdall.py
heimdall/res/heimdall/hooks/pre-commit
heimdall/res/heimdall/hooks/temp-pre-commit
heimdall/res/heimdall/info/exclude
heimdall/secret/__init__.py
heimdall/secret/manager.py
heimdall/secret/secret.py
heimdall/template/__init__.py
heimdall/template/manager.py
heimdall/template/template.py
heimdall/test/__init__.py
heimdall/test/__main__.py
heimdall/test/codescan_plugin_manager_test.py
heimdall/test/shannon_entropy_test.py
heimdall/test/test_regex_check.py