Metadata-Version: 1.1
Name: git-heimdall
Version: 0.0.4.dev0
Summary: Tool to scan staged files before commit and provide functionality to create configuration file from secret                    templates
Home-page: UNKNOWN
Author: Sunny Sharma
Author-email: sunnysharmagts@gmail.com
License: UNKNOWN
Platform: UNKNOWN
Classifier: Development Status :: 2 - Pre-Alpha
Classifier: Intended Audience :: Developers
Classifier: Intended Audience :: End Users/Desktop
Classifier: Intended Audience :: Information Technology
Classifier: License :: OSI Approved :: MIT License
Classifier: Operating System :: OS Independent
Classifier: Programming Language :: Python :: 3
Classifier: Topic :: System :: Monitoring
